utilshub.py
utilshub-0.4.dist-info/METADATA
utilshub-0.4.dist-info/WHEEL
utilshub-0.4.dist-info/top_level.txt
utilshub-0.4.dist-info/RECORD
