Metadata-Version: 2.4
Name: utilshub
Version: 0.4
Summary: Utility functions collection
Home-page: 
Author: tester641114
Author-email: guesthello01@gmail.com
Classifier: Programming Language :: Python :: 3
Requires-Python: >=3.6
Dynamic: author
Dynamic: author-email
Dynamic: classifier
Dynamic: requires-python
Dynamic: summary
